aiopyopenttdadmin/__init__.py
aiopyopenttdadmin/admin.py
pyopenttdadmin/__init__.py
pyopenttdadmin/admin.py
pyopenttdadmin/enums.py
pyopenttdadmin/packet.py
pyopenttdadmin-1.0.3.dist-info/LICENSE
pyopenttdadmin-1.0.3.dist-info/METADATA
pyopenttdadmin-1.0.3.dist-info/WHEEL
pyopenttdadmin-1.0.3.dist-info/top_level.txt
pyopenttdadmin-1.0.3.dist-info/RECORD
