Metadata-Version: 2.2
Name: pyOpenTTDAdmin
Version: 1.0.3
Summary: Python library to communicate with OpenTTD Admin port
Home-page: https://github.com/liki-mc/pyOpenTTDAdmin/
Author: liki-mc
License: MIT
License-File: LICENSE
Dynamic: author
Dynamic: description
Dynamic: description-content-type
Dynamic: home-page
Dynamic: license
Dynamic: summary
